vivarium_helpers/__about__.py
vivarium_helpers/__init__.py
vivarium_helpers/_version.py
vivarium_helpers/hobbs.py
vivarium_helpers/id_helper.py
vivarium_helpers/prob_utils.py
vivarium_helpers/utils.py
vivarium_helpers/lbwsg/__init__.py
vivarium_helpers/lbwsg/demography.py
vivarium_helpers/lbwsg/lbwsg.py
vivarium_helpers/lbwsg/lbwsg_plots.py
vivarium_helpers/prob_distributions/__init__.py
vivarium_helpers/prob_distributions/descriptive_stats.py
vivarium_helpers/prob_distributions/fit.py
vivarium_helpers/prob_distributions/fit_approx.py
vivarium_helpers/prob_distributions/fit_exact.py
vivarium_helpers/prob_distributions/plotting.py
vivarium_helpers/prob_distributions/sampling.py
vivarium_helpers/vph_output/__init__.py
vivarium_helpers/vph_output/cleaning.py
vivarium_helpers/vph_output/loading.py
vivarium_helpers/vph_output/measures.py
vivarium_helpers/vph_output/operations.py
vivarium_helpers-0.4.4.dist-info/licenses/AUTHORS.rst
vivarium_helpers-0.4.4.dist-info/licenses/LICENSE
vivarium_helpers-0.4.4.dist-info/METADATA
vivarium_helpers-0.4.4.dist-info/WHEEL
vivarium_helpers-0.4.4.dist-info/top_level.txt
vivarium_helpers-0.4.4.dist-info/RECORD
