Metadata-Version: 2.4
Name: vivarium_helpers
Version: 0.4.4
Summary: Tools maintained by the research side of the IHME simluation science team.
Home-page: https://github.com/ihmeuw/vivarium_helpers
Author: Nathaniel Blair-Stahn, Beatrix Haddock
Author-email: beatrixh@uw.com
License: BSD-3-Clause
License-File: LICENSE
License-File: AUTHORS.rst
Requires-Dist: vivarium_dependencies[db_queries,loguru,numpy,pandas,scipy]
Requires-Dist: vivarium_build_utils<3.0.0,>=2.1.1
Provides-Extra: docs
Requires-Dist: vivarium_dependencies[sphinx]; extra == "docs"
Provides-Extra: test
Requires-Dist: vivarium_dependencies[pytest]; extra == "test"
Provides-Extra: dev
Requires-Dist: vivarium_dependencies[sphinx]; extra == "dev"
Requires-Dist: vivarium_dependencies[pytest]; extra == "dev"
Requires-Dist: vivarium_dependencies[lint]; extra == "dev"
Dynamic: author
Dynamic: author-email
Dynamic: description
Dynamic: home-page
Dynamic: license
Dynamic: license-file
Dynamic: provides-extra
Dynamic: requires-dist
Dynamic: summary
